alphanucleo/__init__.py
alphanucleo-0.0.1a1.dist-info/METADATA
alphanucleo-0.0.1a1.dist-info/WHEEL
alphanucleo-0.0.1a1.dist-info/licenses/LICENSE
alphanucleo-0.0.1a1.dist-info/RECORD
